suretime/__init__.py
suretime/_cache.py
suretime/_clock.py
suretime/_error.py
suretime/_formatting.py
suretime/_generic_zone.py
suretime/_global.py
suretime/_mapping.py
suretime/_model.py
suretime/_setup.py
suretime/_type.py
suretime/_zone.py
suretime-0.2.0.dist-info/LICENSE.txt
suretime-0.2.0.dist-info/WHEEL
suretime-0.2.0.dist-info/METADATA
suretime-0.2.0.dist-info/RECORD
