Metadata-Version: 2.1
Name: suretime
Version: 0.2.0
Summary: Handle IANA timezones and fully resolved timestamps and intervals on all platforms
Home-page: https://github.com/dmyersturnbull/suretime
License: Apache-2.0
Keywords: timezone,zoneinfo,datetime,timestamp
Author: Douglas Myers-Turnbull
Maintainer: Douglas Myers-Turnbull
Requires-Python: >=3.9,<4.0
Classifier: Development Status :: 3 - Alpha
Classifier: Intended Audience :: Developers
Classifier: License :: OSI Approved :: Apache Software License
Classifier: Natural Language :: English
Classifier: Operating System :: OS Independent
Classifier: Programming Language :: Python :: 3
Classifier: Programming Language :: Python :: 3 :: Only
Classifier: Programming Language :: Python :: 3.10
Classifier: Programming Language :: Python :: 3.9
Classifier: Topic :: Software Development :: Libraries :: Python Modules
Requires-Dist: defusedxml (>=0.7,<1.0)
Requires-Dist: ntplib (>=0.4,<1.0)
Project-URL: CI, https://github.com/dmyersturnbull/suretime/actions
Project-URL: Documentation, https://suretime.readthedocs.io
Project-URL: Download, https://pypi.org/project/suretime/
Project-URL: Issues, https://github.com/dmyersturnbull/suretime/issues
Project-URL: Repository, https://github.com/dmyersturnbull/suretime
